{
  "props": [
    {
      "label": "daim_1",
      "width": 60,
      "height": 70,
      "center": {
        "x": 29,
        "y": 67
      },
      "avail": [
        {
          "fromT": 9,
          "to": 13
        }
      ],
      "list": [
        {
          "x": 3111,
          "y": 4202
        }
      ]
    },
    {
      "label": "daim_1",
      "width": 60,
      "height": 70,
      "center": {
        "x": 29,
        "y": 67
      },
      "avail": [
        {
          "fromT": 22,
          "to": 2,
          "dates": [
            [
              "21-03",
              "21-12"
            ]
          ]
        }
      ],
      "list": [
        {
          "x": 3111,
          "y": 4202
        }
      ]
    },
    {
      "label": "daim_1",
      "width": 60,
      "height": 70,
      "center": {
        "x": 29,
        "y": 67
      },
      "avail": [
        {
          "fromT": 15,
          "to": 18,
          "dates": [
            [
              "21-03",
              "21-12"
            ]
          ]
        }
      ],
      "list": [
        {
          "x": 2341,
          "y": 4149
        }
      ]
    },
    {
      "label": "daim_1",
      "width": 60,
      "height": 70,
      "center": {
        "x": 29,
        "y": 67
      },
      "avail": [
        {
          "fromT": 6,
          "to": 8,
          "dates": [
            [
              "21-03",
              "21-12"
            ]
          ]
        }
      ],
      "list": [
        {
          "x": 774,
          "y": 3337
        }
      ]
    },
    {
      "label": "daim_1",
      "width": 60,
      "height": 70,
      "center": {
        "x": 29,
        "y": 67
      },
      "avail": [
        {
          "fromT": 19,
          "to": 22
        }
      ],
      "list": [
        {
          "x": 980,
          "y": 2311
        }
      ]
    },
    {
      "label": "daim_1",
      "width": 60,
      "height": 70,
      "center": {
        "x": 29,
        "y": 67
      },
      "avail": [
        {
          "fromT": 4,
          "to": 8,
          "dates": [
            [
              "21-03",
              "21-12"
            ]
          ]
        }
      ],
      "list": [
        {
          "x": 3999,
          "y": 5362
        }
      ]
    },
    {
      "label": "daim_1",
      "width": 60,
      "height": 70,
      "center": {
        "x": 29,
        "y": 67
      },
      "avail": [
        {
          "fromT": 21,
          "to": 1,
          "dates": [
            [
              "21-03",
              "21-12"
            ]
          ]
        }
      ],
      "list": [
        {
          "x": 2688,
          "y": 5119
        }
      ]
    },
    {
      "label": "daim_1",
      "width": 60,
      "height": 70,
      "center": {
        "x": 29,
        "y": 67
      },
      "avail": [
        {
          "fromT": 15,
          "to": 19,
          "dates": [
            [
              "21-03",
              "21-12"
            ]
          ]
        }
      ],
      "list": [
        {
          "x": 2905,
          "y": 2255
        }
      ]
    },
    {
      "label": "daim_2",
      "width": 60,
      "height": 70,
      "center": {
        "x": 31,
        "y": 67
      },
      "avail": [
        {
          "fromT": 8,
          "to": 11
        }
      ],
      "list": [
        {
          "x": 4587,
          "y": 3158
        }
      ]
    },
    {
      "label": "daim_2",
      "width": 60,
      "height": 70,
      "center": {
        "x": 31,
        "y": 67
      },
      "avail": [
        {
          "fromT": 18,
          "to": 23,
          "dates": [
            [
              "21-03",
              "21-12"
            ]
          ]
        }
      ],
      "list": [
        {
          "x": 4587,
          "y": 3158
        }
      ]
    },
    {
      "label": "daim_2",
      "width": 60,
      "height": 70,
      "center": {
        "x": 31,
        "y": 67
      },
      "avail": [
        {
          "fromT": 10,
          "to": 15,
          "dates": [
            [
              "21-03",
              "21-12"
            ]
          ]
        }
      ],
      "list": [
        {
          "x": 2266,
          "y": 5570
        }
      ]
    },
    {
      "label": "daim_2",
      "width": 60,
      "height": 70,
      "center": {
        "x": 31,
        "y": 67
      },
      "avail": [
        {
          "fromT": 10,
          "to": 15,
          "dates": [
            [
              "21-03",
              "21-12"
            ]
          ]
        }
      ],
      "list": [
        {
          "x": 2266,
          "y": 5570
        }
      ]
    },
    {
      "label": "daim_2",
      "width": 60,
      "height": 70,
      "center": {
        "x": 31,
        "y": 67
      },
      "avail": [
        {
          "fromT": 12,
          "to": 17,
          "dates": [
            [
              "21-03",
              "21-12"
            ]
          ]
        }
      ],
      "list": [
        {
          "x": 1900,
          "y": 3784
        }
      ]
    },
    {
      "label": "daim_2",
      "width": 60,
      "height": 70,
      "center": {
        "x": 31,
        "y": 67
      },
      "avail": [
        {
          "fromT": 17,
          "to": 20,
          "dates": [
            [
              "21-03",
              "21-12"
            ]
          ]
        }
      ],
      "list": [
        {
          "x": 1426,
          "y": 4654
        }
      ]
    },
    {
      "label": "daim_2",
      "width": 60,
      "height": 70,
      "center": {
        "x": 31,
        "y": 67
      },
      "avail": [
        {
          "fromT": 11,
          "to": 15
        }
      ],
      "list": [
        {
          "x": 3912,
          "y": 2549
        }
      ]
    },
    {
      "label": "lucioles_1",
      "width": 55,
      "height": 55,
      "center": {
        "x": 7,
        "y": 44
      },
      "avail": [
        {
          "fromT": 21,
          "to": 5
        }
      ],
      "list": [
        {
          "x": 3604,
          "y": 2006
        },
        {
          "x": 2490,
          "y": 2196
        },
        {
          "x": 1267,
          "y": 3355
        },
        {
          "x": 1951,
          "y": 4226
        },
        {
          "x": 1316,
          "y": 4945
        },
        {
          "x": 898,
          "y": 4898
        },
        {
          "x": 1032,
          "y": 5340
        },
        {
          "x": 2309,
          "y": 5739
        },
        {
          "x": 3272,
          "y": 5462
        },
        {
          "x": 3588,
          "y": 4931
        },
        {
          "x": 5024,
          "y": 5723
        },
        {
          "x": 5070,
          "y": 4207
        },
        {
          "x": 4542,
          "y": 3554
        },
        {
          "x": 4905,
          "y": 3008
        },
        {
          "x": 3842,
          "y": 3267
        },
        {
          "x": 3713,
          "y": 4000
        },
        {
          "x": 3205,
          "y": 4180
        },
        {
          "x": 2953,
          "y": 3999
        },
        {
          "x": 2089,
          "y": 2775
        },
        {
          "x": 3577,
          "y": 2638
        },
        {
          "x": 650,
          "y": 500
        },
        {
          "x": 1383,
          "y": 1429
        }
      ]
    },
    {
      "label": "lucioles_2",
      "width": 80,
      "height": 50,
      "center": {
        "x": 38,
        "y": 30
      },
      "avail": [
        {
          "fromT": 21,
          "to": 5
        }
      ],
      "list": [
        {
          "x": 4219,
          "y": 1933
        },
        {
          "x": 3681,
          "y": 2024
        },
        {
          "x": 2769,
          "y": 2269
        },
        {
          "x": 1805,
          "y": 2587
        },
        {
          "x": 740,
          "y": 2506
        },
        {
          "x": 1310,
          "y": 3404
        },
        {
          "x": 740,
          "y": 2506
        },
        {
          "x": 1482,
          "y": 3990
        },
        {
          "x": 3000,
          "y": 4056
        },
        {
          "x": 3641,
          "y": 3972
        },
        {
          "x": 3405,
          "y": 4333
        },
        {
          "x": 3747,
          "y": 5435
        },
        {
          "x": 1179,
          "y": 5045
        },
        {
          "x": 4680,
          "y": 3564
        },
        {
          "x": 4455,
          "y": 3019
        },
        {
          "x": 1747,
          "y": 1352
        }
      ]
    },
    {
      "label": "bergeronette_g",
      "width": 15,
      "height": 14,
      "center": {
        "x": 7,
        "y": 13
      },
      "avail": [
        {
          "fromT": 7,
          "to": 11
        }
      ],
      "list": [
        {
          "x": 4407,
          "y": 5222
        }
      ]
    },
    {
      "label": "bergeronette_g",
      "width": 15,
      "height": 14,
      "center": {
        "x": 14,
        "y": 18
      },
      "avail": [
        {
          "fromT": 11,
          "to": 15
        }
      ],
      "list": [
        {
          "x": 4824,
          "y": 5296
        }
      ]
    },
    {
      "label": "bergeronette_g",
      "width": 15,
      "height": 14,
      "center": {
        "x": 7,
        "y": 13
      },
      "avail": [
        {
          "fromT": 16,
          "to": 19
        }
      ],
      "list": [
        {
          "x": 4471,
          "y": 5593
        }
      ]
    },
    {
      "label": "bergeronette_g",
      "width": 15,
      "height": 14,
      "center": {
        "x": 7,
        "y": 13
      },
      "avail": [
        {
          "fromT": 10,
          "to": 13,
          "dates": [
            [
              "21-03",
              "21-12"
            ]
          ]
        }
      ],
      "list": [
        {
          "x": 3944,
          "y": 5734
        }
      ]
    },
    {
      "label": "bergeronette_g",
      "width": 15,
      "height": 14,
      "center": {
        "x": 7,
        "y": 13
      },
      "avail": [
        {
          "fromT": 8,
          "to": 14
        }
      ],
      "list": [
        {
          "x": 3830,
          "y": 5468
        }
      ]
    },
    {
      "label": "bergeronette_g",
      "width": 15,
      "height": 14,
      "center": {
        "x": 7,
        "y": 13
      },
      "avail": [
        {
          "fromT": 12,
          "to": 17,
          "dates": [
            [
              "21-03",
              "21-12"
            ]
          ]
        }
      ],
      "list": [
        {
          "x": 3683,
          "y": 5123
        }
      ]
    },
    {
      "label": "bergeronette_g",
      "width": 15,
      "height": 14,
      "center": {
        "x": 7,
        "y": 13
      },
      "avail": [
        {
          "fromT": 15,
          "to": 18,
          "dates": [
            [
              "21-03",
              "21-12"
            ]
          ]
        }
      ],
      "list": [
        {
          "x": 4255,
          "y": 5170
        }
      ]
    },
    {
      "label": "bergeronette_g",
      "width": 15,
      "height": 14,
      "center": {
        "x": 7,
        "y": 13
      },
      "avail": [
        {
          "fromT": 10,
          "to": 14,
          "dates": [
            [
              "21-03",
              "21-12"
            ]
          ]
        }
      ],
      "list": [
        {
          "x": 4640,
          "y": 4762
        }
      ]
    },
    {
      "label": "bergeronette_g",
      "width": 15,
      "height": 14,
      "center": {
        "x": 7,
        "y": 13
      },
      "avail": [
        {
          "fromT": 13,
          "to": 17,
          "dates": [
            [
              "21-03",
              "21-12"
            ]
          ]
        }
      ],
      "list": [
        {
          "x": 5114,
          "y": 4358
        }
      ]
    },
    {
      "label": "bergeronette_g",
      "width": 15,
      "height": 14,
      "center": {
        "x": 7,
        "y": 13
      },
      "avail": [
        {
          "fromT": 8,
          "to": 12,
          "dates": [
            [
              "21-03",
              "21-12"
            ]
          ]
        }
      ],
      "list": [
        {
          "x": 2083,
          "y": 2823
        }
      ]
    },
    {
      "label": "lapin_1",
      "width": 22,
      "height": 26,
      "center": {
        "x": 7,
        "y": 25
      },
      "avail": [
        {
          "fromT": 8,
          "to": 12,
          "dates": [
            [
              "21-03",
              "21-12"
            ]
          ]
        }
      ],
      "list": [
        {
          "x": 3579,
          "y": 4216
        }
      ]
    },
    {
      "label": "lapin_1",
      "width": 22,
      "height": 26,
      "center": {
        "x": 7,
        "y": 25
      },
      "avail": [
        {
          "fromT": 13,
          "to": 17
        }
      ],
      "list": [
        {
          "x": 4888,
          "y": 3367
        }
      ]
    },
    {
      "label": "lapin_1",
      "width": 22,
      "height": 26,
      "center": {
        "x": 7,
        "y": 25
      },
      "avail": [
        {
          "fromT": 15,
          "to": 19,
          "dates": [
            [
              "21-03",
              "21-12"
            ]
          ]
        }
      ],
      "list": [
        {
          "x": 1845,
          "y": 5163
        }
      ]
    },
    {
      "label": "lapin_1",
      "width": 22,
      "height": 26,
      "center": {
        "x": 7,
        "y": 25
      },
      "avail": [
        {
          "fromT": 8,
          "to": 11,
          "dates": [
            [
              "21-03",
              "21-12"
            ]
          ]
        }
      ],
      "list": [
        {
          "x": 1268,
          "y": 3040
        }
      ]
    },
    {
      "label": "lapin_1",
      "width": 22,
      "height": 26,
      "center": {
        "x": 7,
        "y": 25
      },
      "avail": [
        {
          "fromT": 11,
          "to": 15,
          "dates": [
            [
              "21-03",
              "21-12"
            ]
          ]
        }
      ],
      "list": [
        {
          "x": 4125,
          "y": 1949
        }
      ]
    },
    {
      "label": "lapin_1",
      "width": 22,
      "height": 26,
      "center": {
        "x": 7,
        "y": 25
      },
      "avail": [
        {
          "fromT": 8,
          "to": 12,
          "dates": [
            [
              "21-03",
              "21-12"
            ]
          ]
        }
      ],
      "list": [
        {
          "x": 5006,
          "y": 5494
        }
      ]
    },
    {
      "label": "cerf",
      "width": 58,
      "height": 86,
      "center": {
        "x": 26,
        "y": 85
      },
      "avail": [
        {
          "fromT": 7,
          "to": 8
        }
      ],
      "list": [
        {
          "x": 3355,
          "y": 4151
        }
      ]
    },
    {
      "label": "cerf",
      "width": 58,
      "height": 86,
      "center": {
        "x": 26,
        "y": 85
      },
      "avail": [
        {
          "fromT": 18,
          "to": 19
        }
      ],
      "list": [
        {
          "x": 968,
          "y": 4847
        }
      ]
    },
    {
      "label": "ours_sleep",
      "width": 89,
      "height": 78,
      "center": {
        "x": 33,
        "y": 77
      },
      "avail": [
        {
          "fromT": 20,
          "to": 4,
          "dates": [
            [
              "21-03",
              "21-12"
            ]
          ]
        }
      ],
      "list": [
        {
          "x": 2189,
          "y": 2963
        }
      ]
    },
    {
      "label": "ecureuil_d",
      "width": 14,
      "height": 19,
      "center": {
        "x": 8,
        "y": 18
      },
      "avail": [
        {
          "fromT": 13,
          "to": 16,
          "dates": [
            [
              "21-03",
              "21-12"
            ]
          ]
        }
      ],
      "list": [
        {
          "x": 3162,
          "y": 4140
        }
      ]
    },
    {
      "label": "ecureuil_d",
      "width": 14,
      "height": 19,
      "center": {
        "x": 8,
        "y": 18
      },
      "avail": [
        {
          "fromT": 9,
          "to": 12,
          "dates": [
            [
              "21-03",
              "21-12"
            ]
          ]
        }
      ],
      "list": [
        {
          "x": 4003,
          "y": 3096
        }
      ]
    },
    {
      "label": "ecureuil_d",
      "width": 14,
      "height": 19,
      "center": {
        "x": 8,
        "y": 18
      },
      "avail": [
        {
          "fromT": 10,
          "to": 13
        }
      ],
      "list": [
        {
          "x": 4447,
          "y": 5361
        }
      ]
    },
    {
      "label": "ecureuil_d",
      "width": 14,
      "height": 19,
      "center": {
        "x": 8,
        "y": 18
      },
      "avail": [
        {
          "fromT": 17,
          "to": 18,
          "dates": [
            [
              "21-03",
              "21-12"
            ]
          ]
        }
      ],
      "list": [
        {
          "x": 3784,
          "y": 5726
        }
      ]
    },
    {
      "label": "ecureuil_d",
      "width": 14,
      "height": 19,
      "center": {
        "x": 8,
        "y": 18
      },
      "avail": [
        {
          "fromT": 11,
          "to": 16,
          "dates": [
            [
              "21-03",
              "21-12"
            ]
          ]
        }
      ],
      "list": [
        {
          "x": 1532,
          "y": 5050
        },
        {
          "x": 1637,
          "y": 2870
        },
        {
          "x": 1589,
          "y": 3947
        }
      ]
    },
    {
      "label": "ecureuil_d",
      "width": 14,
      "height": 19,
      "center": {
        "x": 8,
        "y": 18
      },
      "avail": [
        {
          "fromT": 8,
          "to": 11,
          "dates": [
            [
              "21-03",
              "21-12"
            ]
          ]
        }
      ],
      "list": [
        {
          "x": 630,
          "y": 4935
        }
      ]
    },
    {
      "label": "ecureuil_d",
      "width": 14,
      "height": 19,
      "center": {
        "x": 8,
        "y": 18
      },
      "avail": [
        {
          "fromT": 8,
          "to": 11,
          "dates": [
            [
              "21-03",
              "21-12"
            ]
          ]
        }
      ],
      "list": [
        {
          "x": 235,
          "y": 3433
        }
      ]
    },
    {
      "label": "ecureuil_d",
      "width": 14,
      "height": 19,
      "center": {
        "x": 8,
        "y": 18
      },
      "avail": [
        {
          "fromT": 10,
          "to": 15,
          "dates": [
            [
              "21-03",
              "21-12"
            ]
          ]
        }
      ],
      "list": [
        {
          "x": 695,
          "y": 2320
        }
      ]
    },
    {
      "label": "ecureuil_d",
      "width": 14,
      "height": 19,
      "center": {
        "x": 8,
        "y": 18
      },
      "avail": [
        {
          "fromT": 14,
          "to": 18,
          "dates": [
            [
              "21-03",
              "21-12"
            ]
          ]
        }
      ],
      "list": [
        {
          "x": 3050,
          "y": 1931
        },
        {
          "x": 2237,
          "y": 5602
        },
        {
          "x": 4546,
          "y": 4929
        }
      ]
    },
    {
      "label": "ecureuil_d",
      "width": 14,
      "height": 19,
      "center": {
        "x": 8,
        "y": 18
      },
      "avail": [
        {
          "fromT": 17,
          "to": 19,
          "dates": [
            [
              "21-03",
              "21-12"
            ]
          ]
        }
      ],
      "list": [
        {
          "x": 3650,
          "y": 1936
        }
      ]
    },
    {
      "label": "ecureuil_d",
      "width": 14,
      "height": 19,
      "center": {
        "x": 8,
        "y": 18
      },
      "avail": [
        {
          "fromT": 17,
          "to": 19,
          "dates": [
            [
              "21-03",
              "21-12"
            ]
          ]
        }
      ],
      "list": [
        {
          "x": 4564,
          "y": 2551
        }
      ]
    },
    {
      "label": "groupe_corbeau",
      "width": 50,
      "height": 33,
      "center": {
        "x": 31,
        "y": 31
      },
      "avail": [
        {
          "fromT": 18,
          "to": 2
        }
      ],
      "list": [
        {
          "x": 4656,
          "y": 1557
        }
      ]
    },
    {
      "label": "groupe_corbeau",
      "width": 50,
      "height": 33,
      "center": {
        "x": 31,
        "y": 31
      },
      "avail": [
        {
          "fromT": 4,
          "to": 10
        }
      ],
      "list": [
        {
          "x": 4857,
          "y": 1441
        }
      ]
    },
    {
      "label": "groupe_corbeau",
      "width": 50,
      "height": 33,
      "center": {
        "x": 31,
        "y": 31
      },
      "avail": [
        {
          "fromT": 12,
          "to": 17
        }
      ],
      "list": [
        {
          "x": 4569,
          "y": 1457
        }
      ]
    },
    {
      "label": "groupe_corbeau",
      "width": 50,
      "height": 33,
      "center": {
        "x": 31,
        "y": 31
      },
      "avail": [
        {
          "fromT": 21,
          "to": 3
        }
      ],
      "list": [
        {
          "x": 4862,
          "y": 1294
        }
      ]
    },
    {
      "label": "groupe_corbeau",
      "width": 50,
      "height": 33,
      "center": {
        "x": 31,
        "y": 31
      },
      "avail": [
        {
          "fromT": 13,
          "to": 20
        }
      ],
      "list": [
        {
          "x": 4783,
          "y": 1252
        }
      ]
    },
    {
      "label": "groupe_corbeau",
      "width": 50,
      "height": 33,
      "center": {
        "x": 31,
        "y": 31
      },
      "avail": [
        {
          "fromT": 10,
          "to": 15
        }
      ],
      "list": [
        {
          "x": 4388,
          "y": 1306
        }
      ]
    },
    {
      "label": "groupe_corbeau",
      "width": 50,
      "height": 33,
      "center": {
        "x": 31,
        "y": 31
      },
      "avail": [
        {
          "fromT": 14,
          "to": 19
        }
      ],
      "list": [
        {
          "x": 4478,
          "y": 1027
        }
      ]
    },
    {
      "label": "groupe_corbeau",
      "width": 50,
      "height": 33,
      "center": {
        "x": 31,
        "y": 31
      },
      "avail": [
        {
          "fromT": 20,
          "to": 2
        }
      ],
      "list": [
        {
          "x": 4381,
          "y": 761
        }
      ]
    },
    {
      "label": "groupe_corbeau",
      "width": 50,
      "height": 33,
      "center": {
        "x": 31,
        "y": 31
      },
      "avail": [
        {
          "fromT": 12,
          "to": 18
        }
      ],
      "list": [
        {
          "x": 4830,
          "y": 441
        }
      ]
    },
    {
      "label": "groupe_corbeau",
      "width": 50,
      "height": 33,
      "center": {
        "x": 31,
        "y": 31
      },
      "avail": [
        {
          "fromT": 3,
          "to": 9
        }
      ],
      "list": [
        {
          "x": 5040,
          "y": 775
        }
      ]
    },
    {
      "label": "groupe_corbeau",
      "width": 50,
      "height": 33,
      "center": {
        "x": 31,
        "y": 31
      },
      "avail": [
        {
          "fromT": 16,
          "to": 22
        }
      ],
      "list": [
        {
          "x": 5138,
          "y": 640
        }
      ]
    },
    {
      "label": "groupe_corbeau",
      "width": 50,
      "height": 33,
      "center": {
        "x": 31,
        "y": 31
      },
      "avail": [
        {
          "fromT": 7,
          "to": 11
        }
      ],
      "list": [
        {
          "x": 5120,
          "y": 1027
        }
      ]
    },
    {
      "label": "groupe_corbeau",
      "width": 50,
      "height": 33,
      "center": {
        "x": 31,
        "y": 31
      },
      "avail": [
        {
          "fromT": 17,
          "to": 20
        }
      ],
      "list": [
        {
          "x": 3919,
          "y": 1916
        }
      ]
    },
    {
      "label": "merle",
      "width": 22,
      "height": 19,
      "center": {
        "x": 9,
        "y": 15
      },
      "avail": [
        {
          "fromT": 16,
          "to": 18
        }
      ],
      "list": [
        {
          "x": 4162,
          "y": 5173
        }
      ]
    },
    {
      "label": "merle",
      "width": 22,
      "height": 19,
      "center": {
        "x": 9,
        "y": 15
      },
      "avail": [
        {
          "fromT": 10,
          "to": 14
        }
      ],
      "list": [
        {
          "x": 4797,
          "y": 5178
        }
      ]
    },
    {
      "label": "merle",
      "width": 22,
      "height": 19,
      "center": {
        "x": 9,
        "y": 15
      },
      "avail": [
        {
          "fromT": 17,
          "to": 20
        }
      ],
      "list": [
        {
          "x": 4924,
          "y": 5753
        }
      ]
    },
    {
      "label": "merle",
      "width": 22,
      "height": 19,
      "center": {
        "x": 9,
        "y": 15
      },
      "avail": [
        {
          "fromT": 15,
          "to": 19
        }
      ],
      "list": [
        {
          "x": 3167,
          "y": 4847
        }
      ]
    },
    {
      "label": "merle",
      "width": 22,
      "height": 19,
      "center": {
        "x": 9,
        "y": 15
      },
      "avail": [
        {
          "fromT": 9,
          "to": 14
        }
      ],
      "list": [
        {
          "x": 2453,
          "y": 5330
        }
      ]
    },
    {
      "label": "merle",
      "width": 22,
      "height": 19,
      "center": {
        "x": 9,
        "y": 15
      },
      "avail": [
        {
          "fromT": 15,
          "to": 17
        }
      ],
      "list": [
        {
          "x": 1244,
          "y": 5048
        }
      ]
    },
    {
      "label": "merle",
      "width": 22,
      "height": 19,
      "center": {
        "x": 9,
        "y": 15
      },
      "avail": [
        {
          "fromT": 17,
          "to": 19
        }
      ],
      "list": [
        {
          "x": 3305,
          "y": 4207
        }
      ]
    },
    {
      "label": "merle",
      "width": 22,
      "height": 19,
      "center": {
        "x": 9,
        "y": 15
      },
      "avail": [
        {
          "fromT": 9,
          "to": 12
        }
      ],
      "list": [
        {
          "x": 1795,
          "y": 2051
        }
      ]
    },
    {
      "label": "merle",
      "width": 22,
      "height": 19,
      "center": {
        "x": 9,
        "y": 15
      },
      "avail": [
        {
          "fromT": 13,
          "to": 16
        }
      ],
      "list": [
        {
          "x": 3520,
          "y": 1038
        }
      ]
    },
    {
      "label": "renard",
      "width": 36,
      "height": 34,
      "center": {
        "x": 2,
        "y": 11
      },
      "avail": [
        {
          "fromT": 16,
          "to": 19
        }
      ],
      "list": [
        {
          "x": 3564,
          "y": 4355
        }
      ]
    },
    {
      "label": "renard",
      "width": 36,
      "height": 34,
      "center": {
        "x": 2,
        "y": 11
      },
      "avail": [
        {
          "fromT": 22,
          "to": 3
        }
      ],
      "list": [
        {
          "x": 4648,
          "y": 5003
        }
      ]
    },
    {
      "label": "renard",
      "width": 36,
      "height": 34,
      "center": {
        "x": 2,
        "y": 11
      },
      "avail": [
        {
          "fromT": 21,
          "to": 1
        }
      ],
      "list": [
        {
          "x": 1934,
          "y": 3959
        }
      ]
    },
    {
      "label": "renard",
      "width": 36,
      "height": 34,
      "center": {
        "x": 2,
        "y": 11
      },
      "avail": [
        {
          "fromT": 10,
          "to": 14
        }
      ],
      "list": [
        {
          "x": 2148,
          "y": 2701
        }
      ]
    },
    {
      "label": "renard",
      "width": 36,
      "height": 34,
      "center": {
        "x": 2,
        "y": 11
      },
      "avail": [
        {
          "fromT": 18,
          "to": 20
        }
      ],
      "list": [
        {
          "x": 4367,
          "y": 2654
        }
      ]
    },
    {
      "label": "renard",
      "width": 36,
      "height": 34,
      "center": {
        "x": 2,
        "y": 11
      },
      "avail": [
        {
          "fromT": 10,
          "to": 14
        }
      ],
      "list": [
        {
          "x": 4039,
          "y": 1575
        }
      ]
    },
    {
      "label": "renard",
      "width": 36,
      "height": 34,
      "center": {
        "x": 2,
        "y": 11
      },
      "avail": [
        {
          "fromT": 7,
          "to": 9
        }
      ],
      "list": [
        {
          "x": 4350,
          "y": 5457
        }
      ]
    },
    {
      "label": "lucioles",
      "width": 53,
      "height": 39,
      "center": {
        "x": 7,
        "y": 16
      },
      "avail": [
        {
          "fromT": 21,
          "to": 6
        }
      ],
      "list": [
        {
          "x": 4871,
          "y": 5230
        },
        {
          "x": 5152,
          "y": 5304
        },
        {
          "x": 4550,
          "y": 4885
        },
        {
          "x": 4425,
          "y": 5080
        },
        {
          "x": 3935,
          "y": 5090
        },
        {
          "x": 3493,
          "y": 5379
        },
        {
          "x": 4040,
          "y": 5664
        }
      ]
    },
    {
      "label": "citrouille_2",
      "width": 25,
      "height": 18,
      "action": "pumpkin_find",
      "random_position": true,
      "center": {
        "x": 12,
        "y": 11
      },
      "avail": [
        {
          "fromT": 21,
          "to": 6,
          "event": "halloween"
        }
      ],
      "list": [
        {
          "x": 3133,
          "y": 1695
        },
        {
          "x": 3802,
          "y": 1008
        },
        {
          "x": 4451,
          "y": 1948
        }
      ]
    },
    {
      "label": "citrouille_1",
      "width": 25,
      "height": 18,
      "action": "pumpkin_find",
      "random_position": true,
      "center": {
        "x": 12,
        "y": 11
      },
      "avail": [
        {
          "fromT": 21,
          "to": 6,
          "event": "halloween"
        }
      ],
      "list": [
        {
          "x": 1002,
          "y": 3989
        },
        {
          "x": 2863,
          "y": 3760
        },
        {
          "x": 4404,
          "y": 3750
        }
      ]
    },
    {
      "label": "citrouille_3",
      "width": 21,
      "height": 21,
      "action": "pumpkin_find",
      "random_position": true,
      "center": {
        "x": 9,
        "y": 12
      },
      "avail": [
        {
          "fromT": 21,
          "to": 6,
          "event": "halloween"
        }
      ],
      "list": [
        {
          "x": 4985,
          "y": 5510
        },
        {
          "x": 3938,
          "y": 5789
        },
        {
          "x": 1845,
          "y": 4698
        }
      ]
    }
  ],
  "contribs": [
    {
      "pseudo": "Eryn",
      "slug": "eryn",
      "owner": "Nekota",
      "status": "contributeur",
      "house": {
        "x": 4625,
        "y": 5596,
        "width": 20,
        "height": 36
      },
      "image": {
        "w": 540,
        "h": 960,
        "c": 270
      },
      "avail": [
        {
          "posSlug": "fake",
          "fromT": 5,
          "to": 5,
          "x": 50,
          "y": 50,
          "width": 0,
          "height": 0,
          "center": {
            "x": 0,
            "y": 0
          }
        }
      ]
    },
    {
      "pseudo": "Dhorn",
      "slug": "dhorn",
      "owner": "dhorn",
      "status": "contributeur",
      "house": {
        "x": 4418,
        "y": 5743,
        "width": 20,
        "height": 36
      },
      "image": {
        "w": 540,
        "h": 960,
        "c": 270
      },
      "avail": [
        {
          "posSlug": "fake",
          "fromT": 5,
          "to": 5,
          "x": 50,
          "y": 50,
          "width": 0,
          "height": 0,
          "center": {
            "x": 0,
            "y": 0
          }
        }
      ]
    },
    {
      "pseudo": "Ashka",
      "slug": "ashka",
      "owner": "pocnote",
      "status": "contributeur",
      "house": {
        "x": 4823,
        "y": 5032,
        "width": 20,
        "height": 36
      },
      "image": {
        "w": 540,
        "h": 960,
        "c": 270
      },
      "avail": [
        {
          "posSlug": "fake",
          "fromT": 5,
          "to": 5,
          "x": 50,
          "y": 50,
          "width": 0,
          "height": 0,
          "center": {
            "x": 0,
            "y": 0
          }
        }
      ]
    },
    {
      "pseudo": "Narao",
      "slug": "narao",
      "user_id": 4390,
      "char_index": 1,
      "owner": "nedj",
      "status": "contributeur",
      "house": {
        "x": 3863,
        "y": 5033,
        "width": 20,
        "height": 36
      },
      "image": {
        "w": 400,
        "h": 1000,
        "c": 200
      },
      "avail": [
        {
          "posSlug": "chapeau",
          "fromT": 17,
          "to": 21,
          "x": 2603,
          "y": 4646,
          "width": 119,
          "height": 140,
          "center": {
            "x": 67,
            "y": 138
          }
        }
      ]
    },
    {
      "pseudo": "Mhuire",
      "slug": "mhuire",
      "owner": "hanaen",
      "status": "contributeur",
      "house": {
        "x": 3477,
        "y": 5333,
        "width": 20,
        "height": 36
      },
      "image": {
        "w": 540,
        "h": 960,
        "c": 270
      },
      "avail": [
        {
          "posSlug": "lumiere",
          "fromT": 21,
          "to": 1,
          "x": 3589,
          "y": 4759,
          "width": 36,
          "height": 50,
          "center": {
            "x": 14,
            "y": 49
          }
        }
      ]
    },
    {
      "pseudo": "Lune",
      "slug": "lune",
      "owner": "lyssiar",
      "status": "contributeur",
      "house": {
        "x": 4250,
        "y": 5374,
        "width": 12,
        "height": 22
      },
      "image": {
        "w": 500,
        "h": 1000,
        "c": 250
      },
      "avail": [
        {
          "posSlug": "fake",
          "fromT": 5,
          "to": 5,
          "x": 50,
          "y": 50,
          "width": 0,
          "height": 0,
          "center": {
            "x": 0,
            "y": 0
          }
        }
      ]
    },
    {
      "pseudo": "Elide",
      "slug": "elide",
      "owner": "taps",
      "status": "contributeur",
      "house": {
        "x": 3704,
        "y": 5249,
        "width": 12,
        "height": 22
      },
      "image": {
        "w": 1074,
        "h": 2000,
        "c": 540
      },
      "avail": [
        {
          "posSlug": "fake",
          "fromT": 5,
          "to": 5,
          "x": 50,
          "y": 50,
          "width": 0,
          "height": 0,
          "center": {
            "x": 0,
            "y": 0
          }
        }
      ]
    }
  ]
}